retraction_check/__init__.py
retraction_check/check_bib.py
retraction_check-0.1.0.dist-info/METADATA
retraction_check-0.1.0.dist-info/WHEEL
retraction_check-0.1.0.dist-info/entry_points.txt
retraction_check-0.1.0.dist-info/top_level.txt
retraction_check-0.1.0.dist-info/RECORD
