Metadata-Version: 2.4
Name: retraction-check
Version: 0.1.0
Summary: A Python package to check whether papers in your .bib file have been listed on Retraction Watch
Author-email: Fabian Kneissl <fknssl@gmail.com>
License: MIT
Project-URL: Homepage, https://github.com/codingfabi/retraction_check
Project-URL: Repository, https://github.com/codingfabi/retraction_check
Project-URL: Bug Tracker, https://github.com/codingfabi/retraction_check/issues
Keywords: bibtex,retraction,research,bibliography
Classifier: Development Status :: 3 - Alpha
Classifier: Intended Audience :: Science/Research
Classifier: License :: OSI Approved :: MIT License
Classifier: Operating System :: OS Independent
Classifier: Programming Language :: Python :: 3
Classifier: Programming Language :: Python :: 3.8
Classifier: Programming Language :: Python :: 3.9
Classifier: Programming Language :: Python :: 3.10
Classifier: Programming Language :: Python :: 3.11
Classifier: Programming Language :: Python :: 3.12
Classifier: Topic :: Scientific/Engineering
Classifier: Topic :: Text Processing
Requires-Python: >=3.8
Requires-Dist: bibtexparser
Requires-Dist: requests
Provides-Extra: dev
Requires-Dist: pytest; extra == "dev"
Requires-Dist: pytest-cov; extra == "dev"
Requires-Dist: pytest-mock; extra == "dev"
Requires-Dist: black; extra == "dev"
Requires-Dist: flake8; extra == "dev"
Requires-Dist: mypy; extra == "dev"
